seleniumfw/__init__.py
seleniumfw/api_client.py
seleniumfw/api_server.py
seleniumfw/browser_factory.py
seleniumfw/config.py
seleniumfw/exception.py
seleniumfw/listener_manager.py
seleniumfw/loader.py
seleniumfw/report_generator.py
seleniumfw/report_listener.py
seleniumfw/runner.py
seleniumfw/thread_context.py
seleniumfw/utils.py
seleniumfw-0.3.2.dist-info/licenses/LICENSE
sfw/__init__.py
sfw/cli.py
sfw/templates/jinja/features/feature.feature.j2
sfw/templates/jinja/listeners/listener.py.j2
sfw/templates/jinja/steps/step.py.j2
sfw/templates/jinja/testcases/testcase.py.j2
sfw/templates/jinja/testsuite_collections/testsuite_collection.yml.j2
sfw/templates/jinja/testsuites/testsuite.py.j2
sfw/templates/jinja/testsuites/testsuite.yml.j2
sfw/templates/project/.dockerignore
sfw/templates/project/.env
sfw/templates/project/.env.example
sfw/templates/project/.gitignore
sfw/templates/project/Dockerfile
sfw/templates/project/README.md
sfw/templates/project/__init__.py
sfw/templates/project/main.py
sfw/templates/project/pytest.ini
sfw/templates/project/requirements.txt
sfw/templates/project/.vscode/launch.json
sfw/templates/project/include/environment.py
sfw/templates/project/include/features/login.feature
sfw/templates/project/include/steps/login_steps.py
sfw/templates/project/settings/browser.properties
sfw/templates/project/settings/user.properties
sfw/templates/project/testcases/login.py
sfw/templates/project/testcases/__pycache__/login.cpython-313.pyc
sfw/templates/project/testsuites/login.py
sfw/templates/project/testsuites/login.yml
seleniumfw-0.3.2.dist-info/METADATA
seleniumfw-0.3.2.dist-info/WHEEL
seleniumfw-0.3.2.dist-info/entry_points.txt
seleniumfw-0.3.2.dist-info/top_level.txt
seleniumfw-0.3.2.dist-info/RECORD
