Metadata-Version: 2.4
Name: seleniumfw
Version: 0.3.2
Summary: SeleniumFW - A minimal Selenium test framework that adapt POM
Author-email: Muhamad Badru Salam <badrusalam760@gmail.com>
License: MIT
Requires-Python: >=3.8
License-File: LICENSE
Requires-Dist: selenium
Requires-Dist: python-dotenv
Requires-Dist: pyyaml
Requires-Dist: behave
Requires-Dist: reportlab
Requires-Dist: typer[all]
Requires-Dist: flask
Requires-Dist: requests
Requires-Dist: jinja2
Requires-Dist: apscheduler
Dynamic: license-file
